experiments/__init__.py
experiments/calibration_comparison/__init__.py
experiments/calibration_comparison/create_results_cost_matrix.py
psrcal/__init.__.py
psrcal/__init__.py
psrcal/calibration.py
psrcal/losses.py
psrcal/psr.py
psrcal/utils.py
psrcal/optim/__init__.py
psrcal/optim/example.py
psrcal/optim/fullbatch_optim.py
psrcal/optim/vecmodule.py
psrcal-1.0.0.dist-info/licenses/LICENSE.md
psrcal-1.0.0.dist-info/METADATA
psrcal-1.0.0.dist-info/WHEEL
psrcal-1.0.0.dist-info/top_level.txt
psrcal-1.0.0.dist-info/RECORD
