Metadata-Version: 2.4
Name: psrcal
Version: 1.0.0
Summary: Methods for evaluating and fixing calibration
Home-page: https://github.com/luferrer/psr-calibration
Author: Niko Brummer, Luciana Ferrer, Sergio Alvarez
Author-email: lferrer@dc.uba.ar
Classifier: Programming Language :: Python :: 3
Classifier: License :: OSI Approved :: MIT License
Classifier: Operating System :: OS Independent
Requires-Python: >=3.6
License-File: LICENSE.md
Requires-Dist: matplotlib>=3.5.2
Requires-Dist: numpy>=1.24.1
Requires-Dist: scipy>=1.9.1
Requires-Dist: torch>=2.0.0
Requires-Dist: llreval>=0.0.3
Dynamic: license-file
